[
  {
    "v": 500,
    "vw": 42.2499,
    "o": 42.2499,
    "c": 42.2499,
    "h": 42.2499,
    "l": 42.2499,
    "t": 1557230400000,
    "n": 1
  },
  {
    "v": 171022,
    "vw": 40.061,
    "o": 39.01,
    "c": 41.12,
    "h": 41.205,
    "l": 38.22,
    "t": 1557235800000,
    "n": 1150
  },
  {
    "v": 139140,
    "vw": 41.3257,
    "o": 41.165,
    "c": 41.55,
    "h": 41.56,
    "l": 41.165,
    "t": 1557236700000,
    "n": 1441
  },
  {
    "v": 117683,
    "vw": 41.3607,
    "o": 41.52,
    "c": 40.95,
    "h": 41.62,
    "l": 40.92,
    "t": 1557237600000,
    "n": 1316
  },
  {
    "v": 55153,
    "vw": 41.1294,
    "o": 41,
    "c": 41.48,
    "h": 41.53,
    "l": 40.8105,
    "t": 1557238500000,
    "n": 767
  },
  {
    "v": 69550,
    "vw": 41.2293,
    "o": 41.505,
    "c": 41.02,
    "h": 41.52,
    "l": 40.89,
    "t": 1557239400000,
    "n": 772
  },
  {
    "v": 54369,
    "vw": 41.0559,
    "o": 41.02,
    "c": 41.26,
    "h": 41.3,
    "l": 40.89,
    "t": 1557240300000,
    "n": 870
  },
  {
    "v": 43984,
    "vw": 41.1057,
    "o": 41.25,
    "c": 41.08,
    "h": 41.25,
    "l": 40.94,
    "t": 1557241200000,
    "n": 664
  },
  {
    "v": 46085,
    "vw": 40.9193,
    "o": 41.07,
    "c": 40.93,
    "h": 41.07,
    "l": 40.82,
    "t": 1557242100000,
    "n": 675
  },
  {
    "v": 26000,
    "vw": 40.921,
    "o": 40.95,
    "c": 40.91,
    "h": 41.02,
    "l": 40.84,
    "t": 1557243000000,
    "n": 472
  },
  {
    "v": 50453,
    "vw": 40.8851,
    "o": 40.91,
    "c": 40.9,
    "h": 41,
    "l": 40.82,
    "t": 1557243900000,
    "n": 610
  },
  {
    "v": 30810,
    "vw": 40.9292,
    "o": 40.89,
    "c": 41.01,
    "h": 41.05,
    "l": 40.83,
    "t": 1557244800000,
    "n": 426
  },
  {
    "v": 22178,
    "vw": 41.1044,
    "o": 41.03,
    "c": 41.235,
    "h": 41.25,
    "l": 41.02,
    "t": 1557245700000,
    "n": 342
  },
  {
    "v": 30123,
    "vw": 41.1385,
    "o": 41.23,
    "c": 41.03,
    "h": 41.23,
    "l": 41.03,
    "t": 1557246600000,
    "n": 517
  },
  {
    "v": 33578,
    "vw": 41.0432,
    "o": 41.05,
    "c": 40.95,
    "h": 41.16,
    "l": 40.94,
    "t": 1557247500000,
    "n": 479
  },
  {
    "v": 63529,
    "vw": 40.8385,
    "o": 40.94,
    "c": 40.83,
    "h": 40.96,
    "l": 40.76,
    "t": 1557248400000,
    "n": 690
  },
  {
    "v": 57672,
    "vw": 40.7943,
    "o": 40.84,
    "c": 40.8625,
    "h": 40.9,
    "l": 40.66,
    "t": 1557249300000,
    "n": 713
  },
  {
    "v": 43821,
    "vw": 40.7137,
    "o": 40.82,
    "c": 40.605,
    "h": 40.85,
    "l": 40.57,
    "t": 1557250200000,
    "n": 590
  },
  {
    "v": 53142,
    "vw": 40.6248,
    "o": 40.61,
    "c": 40.6,
    "h": 40.75,
    "l": 40.53,
    "t": 1557251100000,
    "n": 611
  },
  {
    "v": 41148,
    "vw": 40.6511,
    "o": 40.62,
    "c": 40.58,
    "h": 40.815,
    "l": 40.54,
    "t": 1557252000000,
    "n": 578
  },
  {
    "v": 36253,
    "vw": 40.5457,
    "o": 40.59,
    "c": 40.48,
    "h": 40.64,
    "l": 40.44,
    "t": 1557252900000,
    "n": 528
  },
  {
    "v": 52362,
    "vw": 40.5053,
    "o": 40.48,
    "c": 40.48,
    "h": 40.64,
    "l": 40.435,
    "t": 1557253800000,
    "n": 687
  },
  {
    "v": 42642,
    "vw": 40.5445,
    "o": 40.48,
    "c": 40.5723,
    "h": 40.66,
    "l": 40.43,
    "t": 1557254700000,
    "n": 687
  },
  {
    "v": 58894,
    "vw": 40.5454,
    "o": 40.575,
    "c": 40.52,
    "h": 40.63,
    "l": 40.445,
    "t": 1557255600000,
    "n": 842
  },
  {
    "v": 61643,
    "vw": 40.4821,
    "o": 40.535,
    "c": 40.325,
    "h": 40.59,
    "l": 40.32,
    "t": 1557256500000,
    "n": 874
  },
  {
    "v": 127017,
    "vw": 40.0878,
    "o": 40.31,
    "c": 40.1,
    "h": 40.325,
    "l": 40,
    "t": 1557257400000,
    "n": 1580
  },
  {
    "v": 284442,
    "vw": 40.118,
    "o": 40.11,
    "c": 40.15,
    "h": 40.17,
    "l": 40.0357,
    "t": 1557258300000,
    "n": 2676
  },
  {
    "v": 2096,
    "vw": 40.16,
    "o": 40.16,
    "c": 40.16,
    "h": 40.16,
    "l": 40.16,
    "t": 1557259200000,
    "n": 6
  }
]