[
  {
    "v": 357,
    "vw": 192.8099,
    "o": 194.03,
    "c": 194.03,
    "h": 194.03,
    "l": 194.03,
    "t": 1707219900000,
    "n": 10
  },
  {
    "v": 1062,
    "vw": 189.8402,
    "o": 190.5,
    "c": 189,
    "h": 190.5,
    "l": 189,
    "t": 1707223500000,
    "n": 20
  },
  {
    "v": 2878,
    "vw": 185.234,
    "o": 187.79,
    "c": 183,
    "h": 189.5,
    "l": 181,
    "t": 1707224400000,
    "n": 78
  },
  {
    "v": 2699,
    "vw": 182.2361,
    "o": 182.01,
    "c": 184,
    "h": 185,
    "l": 181,
    "t": 1707225300000,
    "n": 42
  },
  {
    "v": 917,
    "vw": 182.0795,
    "o": 182,
    "c": 182.1,
    "h": 182.1,
    "l": 182,
    "t": 1707226200000,
    "n": 16
  },
  {
    "v": 733,
    "vw": 182.8692,
    "o": 183,
    "c": 182.46,
    "h": 183,
    "l": 182.46,
    "t": 1707227100000,
    "n": 19
  },
  {
    "v": 4747,
    "vw": 181.2928,
    "o": 182,
    "c": 182.25,
    "h": 182.25,
    "l": 181,
    "t": 1707228000000,
    "n": 111
  },
  {
    "v": 15113,
    "vw": 182.1029,
    "o": 182.25,
    "c": 181.21,
    "h": 184.9,
    "l": 181,
    "t": 1707228900000,
    "n": 150
  },
  {
    "v": 314178,
    "vw": 178.127,
    "o": 183.89,
    "c": 174.96,
    "h": 184,
    "l": 173.85,
    "t": 1707229800000,
    "n": 4660
  },
  {
    "v": 182659,
    "vw": 175.2697,
    "o": 175.4,
    "c": 174.23,
    "h": 177.4,
    "l": 172.8,
    "t": 1707230700000,
    "n": 2685
  },
  {
    "v": 130002,
    "vw": 171.6158,
    "o": 174.165,
    "c": 171.62,
    "h": 174.8999,
    "l": 168.51,
    "t": 1707231600000,
    "n": 2698
  },
  {
    "v": 82050,
    "vw": 172.0798,
    "o": 171.96,
    "c": 171.7,
    "h": 173.293,
    "l": 171.28,
    "t": 1707232500000,
    "n": 1907
  },
  {
    "v": 78669,
    "vw": 171.1358,
    "o": 171.6,
    "c": 173.07,
    "h": 173.1,
    "l": 169.17,
    "t": 1707233400000,
    "n": 1758
  },
  {
    "v": 78042,
    "vw": 172.2073,
    "o": 173.22,
    "c": 172,
    "h": 173.9,
    "l": 170.9498,
    "t": 1707234300000,
    "n": 1553
  },
  {
    "v": 48368,
    "vw": 171.8745,
    "o": 171.77,
    "c": 172.07,
    "h": 172.49,
    "l": 171.365,
    "t": 1707235200000,
    "n": 1125
  },
  {
    "v": 70072,
    "vw": 172.1354,
    "o": 171.91,
    "c": 171.2852,
    "h": 173.6,
    "l": 170.69,
    "t": 1707236100000,
    "n": 1516
  },
  {
    "v": 51517,
    "vw": 171.0637,
    "o": 171.21,
    "c": 170.79,
    "h": 171.87,
    "l": 170.415,
    "t": 1707237000000,
    "n": 915
  },
  {
    "v": 68496,
    "vw": 169.9141,
    "o": 170.79,
    "c": 170.03,
    "h": 170.98,
    "l": 169.1806,
    "t": 1707237900000,
    "n": 1346
  },
  {
    "v": 83164,
    "vw": 169.9106,
    "o": 169.99,
    "c": 168.62,
    "h": 170.68,
    "l": 168.62,
    "t": 1707238800000,
    "n": 1357
  },
  {
    "v": 118202,
    "vw": 168.6102,
    "o": 168.79,
    "c": 168.095,
    "h": 169.77,
    "l": 166.525,
    "t": 1707239700000,
    "n": 1758
  },
  {
    "v": 49858,
    "vw": 167.5747,
    "o": 168.19,
    "c": 167.795,
    "h": 168.24,
    "l": 167.01,
    "t": 1707240600000,
    "n": 1138
  },
  {
    "v": 54280,
    "vw": 168.4216,
    "o": 167.82,
    "c": 167.82,
    "h": 169.05,
    "l": 167.7052,
    "t": 1707241500000,
    "n": 966
  },
  {
    "v": 56475,
    "vw": 169.0616,
    "o": 167.825,
    "c": 169.46,
    "h": 169.95,
    "l": 167.46,
    "t": 1707242400000,
    "n": 1227
  },
  {
    "v": 73576,
    "vw": 169.7655,
    "o": 169.3,
    "c": 169.545,
    "h": 170.9,
    "l": 168.85,
    "t": 1707243300000,
    "n": 1371
  },
  {
    "v": 109431,
    "vw": 171.327,
    "o": 169.67,
    "c": 173.11,
    "h": 173.12,
    "l": 169.61,
    "t": 1707244200000,
    "n": 1850
  },
  {
    "v": 56678,
    "vw": 172.2219,
    "o": 173.1,
    "c": 172.9841,
    "h": 173.11,
    "l": 171.31,
    "t": 1707245100000,
    "n": 1292
  },
  {
    "v": 61856,
    "vw": 173.4468,
    "o": 172.9771,
    "c": 173.87,
    "h": 173.95,
    "l": 172.8,
    "t": 1707246000000,
    "n": 1365
  },
  {
    "v": 63381,
    "vw": 175.1823,
    "o": 173.935,
    "c": 176.2695,
    "h": 176.48,
    "l": 173.48,
    "t": 1707246900000,
    "n": 1575
  },
  {
    "v": 121848,
    "vw": 177.9033,
    "o": 176.205,
    "c": 179.3514,
    "h": 179.3562,
    "l": 176.205,
    "t": 1707247800000,
    "n": 2439
  },
  {
    "v": 115873,
    "vw": 177.5206,
    "o": 179.37,
    "c": 176.84,
    "h": 179.46,
    "l": 175.72,
    "t": 1707248700000,
    "n": 2231
  },
  {
    "v": 96216,
    "vw": 177.4855,
    "o": 176.835,
    "c": 178.225,
    "h": 178.385,
    "l": 176.27,
    "t": 1707249600000,
    "n": 1573
  },
  {
    "v": 102898,
    "vw": 178.9974,
    "o": 178.104,
    "c": 179.48,
    "h": 179.73,
    "l": 177.9628,
    "t": 1707250500000,
    "n": 2034
  },
  {
    "v": 128892,
    "vw": 179.5017,
    "o": 179.425,
    "c": 180.24,
    "h": 180.715,
    "l": 178.44,
    "t": 1707251400000,
    "n": 2604
  },
  {
    "v": 291769,
    "vw": 181.1278,
    "o": 180.24,
    "c": 182.65,
    "h": 183.06,
    "l": 179.25,
    "t": 1707252300000,
    "n": 5551
  },
  {
    "v": 420,
    "vw": 181.68,
    "o": 182.43,
    "c": 181.3,
    "h": 182.43,
    "l": 181.3,
    "t": 1707253200000,
    "n": 14
  },
  {
    "v": 200,
    "vw": 181.1356,
    "o": 181.19,
    "c": 181.19,
    "h": 181.19,
    "l": 181.19,
    "t": 1707254100000,
    "n": 3
  },
  {
    "v": 488,
    "vw": 181.3195,
    "o": 181,
    "c": 181.58,
    "h": 181.58,
    "l": 181,
    "t": 1707255900000,
    "n": 9
  },
  {
    "v": 192,
    "vw": 181.0099,
    "o": 181.01,
    "c": 181.01,
    "h": 181.01,
    "l": 181.01,
    "t": 1707263100000,
    "n": 2
  },
  {
    "v": 276,
    "vw": 181.9132,
    "o": 181.9999,
    "c": 181.9999,
    "h": 181.9999,
    "l": 181.9999,
    "t": 1707264000000,
    "n": 2
  }
]