[
  {
    "v": 300,
    "vw": 86.6667,
    "o": 87,
    "c": 86.5,
    "h": 87,
    "l": 86.5,
    "t": 1651579200000,
    "n": 2
  },
  {
    "v": 503,
    "vw": 85.8013,
    "o": 85.8,
    "c": 85.8,
    "h": 85.8,
    "l": 85.8,
    "t": 1651580100000,
    "n": 3
  },
  {
    "v": 259,
    "vw": 87.2123,
    "o": 87,
    "c": 87,
    "h": 87,
    "l": 87,
    "t": 1651581900000,
    "n": 3
  },
  {
    "v": 2112,
    "vw": 85.4987,
    "o": 85.8,
    "c": 84.2,
    "h": 86,
    "l": 84.11,
    "t": 1651583700000,
    "n": 45
  },
  {
    "v": 160559,
    "vw": 86.7334,
    "o": 84.22,
    "c": 88.115,
    "h": 89.5,
    "l": 82.5,
    "t": 1651584600000,
    "n": 1983
  },
  {
    "v": 131988,
    "vw": 89.2957,
    "o": 88.75,
    "c": 89.85,
    "h": 90.1476,
    "l": 87.81,
    "t": 1651585500000,
    "n": 1657
  },
  {
    "v": 82682,
    "vw": 88.2319,
    "o": 89.85,
    "c": 85.54,
    "h": 90.01,
    "l": 85.525,
    "t": 1651586400000,
    "n": 1143
  },
  {
    "v": 117167,
    "vw": 86.0759,
    "o": 85.18,
    "c": 86.07,
    "h": 86.64,
    "l": 85.01,
    "t": 1651587300000,
    "n": 999
  },
  {
    "v": 128220,
    "vw": 85.6955,
    "o": 86.34,
    "c": 85.04,
    "h": 86.58,
    "l": 84.8,
    "t": 1651588200000,
    "n": 1350
  },
  {
    "v": 50753,
    "vw": 84.9257,
    "o": 85,
    "c": 84.77,
    "h": 85.33,
    "l": 84.41,
    "t": 1651589100000,
    "n": 852
  },
  {
    "v": 42770,
    "vw": 84.8851,
    "o": 84.77,
    "c": 85.37,
    "h": 85.69,
    "l": 84.285,
    "t": 1651590000000,
    "n": 884
  },
  {
    "v": 32292,
    "vw": 84.9169,
    "o": 85.41,
    "c": 84.89,
    "h": 85.78,
    "l": 84.415,
    "t": 1651590900000,
    "n": 613
  },
  {
    "v": 32592,
    "vw": 85.1632,
    "o": 84.9,
    "c": 85.125,
    "h": 85.73,
    "l": 84.62,
    "t": 1651591800000,
    "n": 707
  },
  {
    "v": 53789,
    "vw": 83.665,
    "o": 85.03,
    "c": 83.12,
    "h": 85.22,
    "l": 82.5201,
    "t": 1651592700000,
    "n": 962
  },
  {
    "v": 49391,
    "vw": 83.1107,
    "o": 83.165,
    "c": 82.59,
    "h": 83.88,
    "l": 82.58,
    "t": 1651593600000,
    "n": 959
  },
  {
    "v": 30857,
    "vw": 82.9965,
    "o": 82.5801,
    "c": 83,
    "h": 83.28,
    "l": 82.5801,
    "t": 1651594500000,
    "n": 606
  },
  {
    "v": 54318,
    "vw": 82.6563,
    "o": 82.9,
    "c": 82.61,
    "h": 82.925,
    "l": 82.52,
    "t": 1651595400000,
    "n": 854
  },
  {
    "v": 66810,
    "vw": 83.0272,
    "o": 82.635,
    "c": 83.55,
    "h": 84.13,
    "l": 82.01,
    "t": 1651596300000,
    "n": 959
  },
  {
    "v": 81429,
    "vw": 83.0535,
    "o": 83.46,
    "c": 83.46,
    "h": 83.63,
    "l": 82.62,
    "t": 1651597200000,
    "n": 943
  },
  {
    "v": 47578,
    "vw": 83.364,
    "o": 83.6,
    "c": 83.305,
    "h": 83.86,
    "l": 82.73,
    "t": 1651598100000,
    "n": 824
  },
  {
    "v": 63823,
    "vw": 83.1673,
    "o": 83.21,
    "c": 84.015,
    "h": 84.015,
    "l": 82.74,
    "t": 1651599000000,
    "n": 702
  },
  {
    "v": 41014,
    "vw": 83.8756,
    "o": 84.06,
    "c": 83.965,
    "h": 84.2092,
    "l": 83.29,
    "t": 1651599900000,
    "n": 753
  },
  {
    "v": 76570,
    "vw": 83.7107,
    "o": 84,
    "c": 83.0101,
    "h": 84.06,
    "l": 83.0101,
    "t": 1651600800000,
    "n": 1091
  },
  {
    "v": 139961,
    "vw": 83.6198,
    "o": 83.105,
    "c": 83.51,
    "h": 84.1,
    "l": 82.11,
    "t": 1651601700000,
    "n": 1869
  },
  {
    "v": 48358,
    "vw": 84.1778,
    "o": 83.56,
    "c": 85.149,
    "h": 85.18,
    "l": 83.44,
    "t": 1651602600000,
    "n": 948
  },
  {
    "v": 53740,
    "vw": 84.9658,
    "o": 85.09,
    "c": 85,
    "h": 85.47,
    "l": 84.28,
    "t": 1651603500000,
    "n": 916
  },
  {
    "v": 64211,
    "vw": 84.624,
    "o": 85.0001,
    "c": 83.99,
    "h": 85.19,
    "l": 83.7901,
    "t": 1651604400000,
    "n": 1171
  },
  {
    "v": 59895,
    "vw": 84.3135,
    "o": 83.995,
    "c": 84.57,
    "h": 84.9,
    "l": 83.79,
    "t": 1651605300000,
    "n": 1478
  },
  {
    "v": 115153,
    "vw": 83.6001,
    "o": 84.47,
    "c": 83.115,
    "h": 84.54,
    "l": 83,
    "t": 1651606200000,
    "n": 2122
  },
  {
    "v": 293537,
    "vw": 82.9033,
    "o": 83.15,
    "c": 82.92,
    "h": 83.93,
    "l": 82.11,
    "t": 1651607100000,
    "n": 4533
  },
  {
    "v": 501,
    "vw": 82.9693,
    "o": 82.93,
    "c": 83,
    "h": 83,
    "l": 82.93,
    "t": 1651609800000,
    "n": 8
  },
  {
    "v": 800,
    "vw": 82.9863,
    "o": 82.98,
    "c": 83,
    "h": 83,
    "l": 82.95,
    "t": 1651613400000,
    "n": 6
  },
  {
    "v": 100,
    "vw": 82.99,
    "o": 82.99,
    "c": 82.99,
    "h": 82.99,
    "l": 82.99,
    "t": 1651614300000,
    "n": 1
  },
  {
    "v": 200,
    "vw": 83.465,
    "o": 83.49,
    "c": 83.44,
    "h": 83.49,
    "l": 83.44,
    "t": 1651619700000,
    "n": 2
  }
]