[
  {
    "v": 1172,
    "vw": 407.072,
    "o": 407,
    "c": 407,
    "h": 407.2,
    "l": 407,
    "t": 1762419600000,
    "n": 33
  },
  {
    "v": 929,
    "vw": 407.3096,
    "o": 407.67,
    "c": 407.5,
    "h": 407.67,
    "l": 407,
    "t": 1762420500000,
    "n": 29
  },
  {
    "v": 168,
    "vw": 408.4042,
    "o": 408,
    "c": 409,
    "h": 409,
    "l": 408,
    "t": 1762421400000,
    "n": 5
  },
  {
    "v": 218,
    "vw": 409.5473,
    "o": 409.53,
    "c": 409.06,
    "h": 409.96,
    "l": 409.06,
    "t": 1762423200000,
    "n": 8
  },
  {
    "v": 907,
    "vw": 411.6235,
    "o": 409.99,
    "c": 418.39,
    "h": 418.39,
    "l": 409.98,
    "t": 1762424100000,
    "n": 33
  },
  {
    "v": 144,
    "vw": 413.4083,
    "o": 413.47,
    "c": 413.47,
    "h": 413.47,
    "l": 413.47,
    "t": 1762428600000,
    "n": 7
  },
  {
    "v": 2120,
    "vw": 412.1712,
    "o": 412.94,
    "c": 411.47,
    "h": 412.94,
    "l": 410,
    "t": 1762430400000,
    "n": 114
  },
  {
    "v": 628,
    "vw": 411.2231,
    "o": 411.06,
    "c": 411.06,
    "h": 411.06,
    "l": 410.9,
    "t": 1762431300000,
    "n": 46
  },
  {
    "v": 10067,
    "vw": 410.5437,
    "o": 412.2,
    "c": 411,
    "h": 412.99,
    "l": 409.99,
    "t": 1762433100000,
    "n": 275
  },
  {
    "v": 6367,
    "vw": 409.8388,
    "o": 412.5,
    "c": 410.18,
    "h": 413,
    "l": 403,
    "t": 1762434000000,
    "n": 325
  },
  {
    "v": 3791,
    "vw": 409.0647,
    "o": 410.08,
    "c": 406,
    "h": 410.8,
    "l": 405,
    "t": 1762434900000,
    "n": 155
  },
  {
    "v": 6053,
    "vw": 402.7929,
    "o": 405,
    "c": 406,
    "h": 408,
    "l": 399.1,
    "t": 1762435800000,
    "n": 347
  },
  {
    "v": 9600,
    "vw": 402.9363,
    "o": 403.05,
    "c": 405,
    "h": 405,
    "l": 400.01,
    "t": 1762436700000,
    "n": 214
  },
  {
    "v": 5316,
    "vw": 401.8665,
    "o": 402,
    "c": 400,
    "h": 404.9,
    "l": 400,
    "t": 1762437600000,
    "n": 120
  },
  {
    "v": 18429,
    "vw": 397.8707,
    "o": 399.93,
    "c": 401.8,
    "h": 401.8,
    "l": 392.3,
    "t": 1762438500000,
    "n": 792
  },
  {
    "v": 353153,
    "vw": 398.7945,
    "o": 402.9,
    "c": 394.175,
    "h": 409.31,
    "l": 391.8,
    "t": 1762439400000,
    "n": 6489
  },
  {
    "v": 216762,
    "vw": 391.212,
    "o": 394.175,
    "c": 381.82,
    "h": 397.07,
    "l": 381.8,
    "t": 1762440300000,
    "n": 6720
  },
  {
    "v": 201938,
    "vw": 383.7702,
    "o": 382.08,
    "c": 382.38,
    "h": 387.57,
    "l": 380.985,
    "t": 1762441200000,
    "n": 6070
  },
  {
    "v": 158227,
    "vw": 381.8453,
    "o": 382.14,
    "c": 381.01,
    "h": 386,
    "l": 379,
    "t": 1762442100000,
    "n": 4826
  },
  {
    "v": 132847,
    "vw": 379.4753,
    "o": 380.97,
    "c": 379.35,
    "h": 382.72,
    "l": 377.51,
    "t": 1762443000000,
    "n": 3701
  },
  {
    "v": 110324,
    "vw": 378.5285,
    "o": 379.35,
    "c": 377.07,
    "h": 379.9,
    "l": 376.49,
    "t": 1762443900000,
    "n": 3502
  },
  {
    "v": 103815,
    "vw": 376.4006,
    "o": 377.2144,
    "c": 376.19,
    "h": 378.02,
    "l": 375.01,
    "t": 1762444800000,
    "n": 3148
  },
  {
    "v": 79839,
    "vw": 378.4918,
    "o": 376.8126,
    "c": 379.61,
    "h": 381,
    "l": 376.13,
    "t": 1762445700000,
    "n": 2612
  },
  {
    "v": 86721,
    "vw": 380.4268,
    "o": 379.4327,
    "c": 382.2823,
    "h": 383.24,
    "l": 379.015,
    "t": 1762446600000,
    "n": 2484
  },
  {
    "v": 69677,
    "vw": 381.7458,
    "o": 381.6078,
    "c": 380.571,
    "h": 383.5499,
    "l": 378.98,
    "t": 1762447500000,
    "n": 2507
  },
  {
    "v": 50301,
    "vw": 381.8178,
    "o": 379.775,
    "c": 384.671,
    "h": 385.24,
    "l": 379,
    "t": 1762448400000,
    "n": 1912
  },
  {
    "v": 46547,
    "vw": 382.5549,
    "o": 384.991,
    "c": 382.475,
    "h": 385,
    "l": 381.38,
    "t": 1762449300000,
    "n": 1740
  },
  {
    "v": 63367,
    "vw": 382.7365,
    "o": 382.09,
    "c": 382.74,
    "h": 384.04,
    "l": 380.0901,
    "t": 1762450200000,
    "n": 2168
  },
  {
    "v": 63766,
    "vw": 382.5893,
    "o": 383.2,
    "c": 383,
    "h": 384.38,
    "l": 379.99,
    "t": 1762451100000,
    "n": 2056
  },
  {
    "v": 63206,
    "vw": 383.2557,
    "o": 383.02,
    "c": 383.57,
    "h": 384.62,
    "l": 381.4,
    "t": 1762452000000,
    "n": 1891
  },
  {
    "v": 81655,
    "vw": 385.7791,
    "o": 384.56,
    "c": 388.42,
    "h": 388.87,
    "l": 383.1,
    "t": 1762452900000,
    "n": 2240
  },
  {
    "v": 83510,
    "vw": 391.381,
    "o": 388.42,
    "c": 394.51,
    "h": 395.1,
    "l": 387.52,
    "t": 1762453800000,
    "n": 2756
  },
  {
    "v": 104632,
    "vw": 393.8776,
    "o": 394.37,
    "c": 394.58,
    "h": 395.355,
    "l": 392.63,
    "t": 1762454700000,
    "n": 2887
  },
  {
    "v": 53964,
    "vw": 392.3901,
    "o": 394.59,
    "c": 390.795,
    "h": 394.99,
    "l": 390.15,
    "t": 1762455600000,
    "n": 1877
  },
  {
    "v": 52925,
    "vw": 393.0311,
    "o": 390.82,
    "c": 394.375,
    "h": 395.14,
    "l": 390.44,
    "t": 1762456500000,
    "n": 1868
  },
  {
    "v": 42050,
    "vw": 392.9655,
    "o": 394.37,
    "c": 392.7599,
    "h": 394.66,
    "l": 391.09,
    "t": 1762457400000,
    "n": 1587
  },
  {
    "v": 44748,
    "vw": 392.0438,
    "o": 391.86,
    "c": 391.775,
    "h": 393,
    "l": 390.38,
    "t": 1762458300000,
    "n": 1835
  },
  {
    "v": 56178,
    "vw": 391.5783,
    "o": 392.11,
    "c": 393.27,
    "h": 393.44,
    "l": 390.41,
    "t": 1762459200000,
    "n": 1893
  },
  {
    "v": 105604,
    "vw": 395.8538,
    "o": 393.175,
    "c": 395.49,
    "h": 398.7,
    "l": 393.175,
    "t": 1762460100000,
    "n": 3017
  },
  {
    "v": 119397,
    "vw": 394.5902,
    "o": 395.76,
    "c": 395.53,
    "h": 397.1499,
    "l": 392.43,
    "t": 1762461000000,
    "n": 3672
  },
  {
    "v": 435915,
    "vw": 395.2347,
    "o": 395.19,
    "c": 395.095,
    "h": 398.7,
    "l": 392.2101,
    "t": 1762461900000,
    "n": 11141
  },
  {
    "v": 2115,
    "vw": 394.9486,
    "o": 394.95,
    "c": 394.95,
    "h": 394.95,
    "l": 394.95,
    "t": 1762462800000,
    "n": 15
  },
  {
    "v": 699,
    "vw": 392.8351,
    "o": 390,
    "c": 395,
    "h": 395,
    "l": 390,
    "t": 1762463700000,
    "n": 18
  },
  {
    "v": 1290,
    "vw": 394.8828,
    "o": 395,
    "c": 394.95,
    "h": 395,
    "l": 394.95,
    "t": 1762464600000,
    "n": 15
  },
  {
    "v": 51,
    "vw": 396.8,
    "o": 396.8,
    "c": 396.8,
    "h": 396.8,
    "l": 396.8,
    "t": 1762467300000,
    "n": 2
  },
  {
    "v": 270,
    "vw": 395.0553,
    "o": 395.865,
    "c": 394.5158,
    "h": 395.865,
    "l": 394.5158,
    "t": 1762468200000,
    "n": 5
  },
  {
    "v": 50,
    "vw": 394.8882,
    "o": 394.89,
    "c": 394.89,
    "h": 394.89,
    "l": 394.89,
    "t": 1762470900000,
    "n": 2
  },
  {
    "v": 100,
    "vw": 394.89,
    "o": 394.89,
    "c": 394.89,
    "h": 394.89,
    "l": 394.89,
    "t": 1762471800000,
    "n": 1
  },
  {
    "v": 83,
    "vw": 394.8999,
    "o": 394.9,
    "c": 394.9,
    "h": 394.9,
    "l": 394.9,
    "t": 1762472700000,
    "n": 3
  },
  {
    "v": 336,
    "vw": 394.9455,
    "o": 394.89,
    "c": 395,
    "h": 395,
    "l": 394.89,
    "t": 1762473600000,
    "n": 16
  },
  {
    "v": 99,
    "vw": 395,
    "o": 395,
    "c": 395,
    "h": 395,
    "l": 395,
    "t": 1762475400000,
    "n": 1
  },
  {
    "v": 171,
    "vw": 394.8947,
    "o": 394.8,
    "c": 395.12,
    "h": 395.12,
    "l": 394.8,
    "t": 1762476300000,
    "n": 4
  }
]